harmonai_tools/__init__.py
harmonai_tools/data/__init__.py
harmonai_tools/data/dataset.py
harmonai_tools/data/utils.py
harmonai_tools/inference/__init__.py
harmonai_tools/inference/generation.py
harmonai_tools/inference/sampling.py
harmonai_tools/inference/utils.py
harmonai_tools/interface/__init__.py
harmonai_tools/interface/gradio.py
harmonai_tools/models/__init__.py
harmonai_tools/models/adp.py
harmonai_tools/models/autoencoders.py
harmonai_tools/models/blocks.py
harmonai_tools/models/bottleneck.py
harmonai_tools/models/conditioners.py
harmonai_tools/models/diffusion.py
harmonai_tools/models/discriminators.py
harmonai_tools/models/factory.py
harmonai_tools/models/local_attention.py
harmonai_tools/models/musicgen.py
harmonai_tools/models/pca.py
harmonai_tools/models/pqmf.py
harmonai_tools/models/pretransforms.py
harmonai_tools/models/wavelets.py
harmonai_tools/training/__init__.py
harmonai_tools/training/autoencoders.py
harmonai_tools/training/diffusion.py
harmonai_tools/training/factory.py
harmonai_tools/training/musicgen.py
harmonai_tools/training/utils.py
harmonai_tools-0.0.7.dist-info/LICENSE
harmonai_tools-0.0.7.dist-info/METADATA
harmonai_tools-0.0.7.dist-info/WHEEL
harmonai_tools-0.0.7.dist-info/top_level.txt
harmonai_tools-0.0.7.dist-info/RECORD
