Metadata-Version: 2.1
Name: harmonai-tools
Version: 0.0.7
Summary: Training and inference tools for generative audio models from Harmonai
Home-page: https://github.com/Harmonai-org/harmonai-tools.git
Author: Harmonai
License-File: LICENSE
Requires-Dist: audiocraft ==1.0.0
Requires-Dist: aeiou ==0.0.20
Requires-Dist: alias-free-torch ==0.0.6
Requires-Dist: auraloss ==0.4.0
Requires-Dist: descript-audio-codec ==1.0.0
Requires-Dist: einops ==0.6.1
Requires-Dist: einops-exts ==0.0.4
Requires-Dist: ema-pytorch ==0.2.3
Requires-Dist: encodec ==0.1.1
Requires-Dist: gradio ==3.42.0
Requires-Dist: importlib-resources ==5.12.0
Requires-Dist: k-diffusion ==0.0.15
Requires-Dist: laion-clap ==1.1.4
Requires-Dist: local-attention ==1.8.6
Requires-Dist: nwt-pytorch ==0.0.4
Requires-Dist: pandas ==2.0.2
Requires-Dist: pedalboard ==0.7.4
Requires-Dist: prefigure ==0.0.9
Requires-Dist: pytorch-lightning ==2.0.9
Requires-Dist: PyWavelets ==1.4.1
Requires-Dist: sentencepiece ==0.1.99
Requires-Dist: s3fs ==2023.6.0
Requires-Dist: torch >=2.0.1
Requires-Dist: torchaudio >=2.0.2
Requires-Dist: torchmetrics ==0.11.4
Requires-Dist: tqdm
Requires-Dist: transformers ==4.33.3
Requires-Dist: v-diffusion-pytorch ==0.0.2
Requires-Dist: vector-quantize-pytorch ==1.6.21
Requires-Dist: wandb ==0.15.4
Requires-Dist: webdataset ==0.2.48
Requires-Dist: x-transformers ==1.16.16
